zeptomail/__init__.py
zeptomail/client.py
zeptomail/errors.py
zeptomail/webhooks/__init__.py
zeptomail/webhooks/models.py
zeptomail/webhooks/router.py
zeptomail_python_api-0.1.5.dist-info/METADATA
zeptomail_python_api-0.1.5.dist-info/WHEEL
zeptomail_python_api-0.1.5.dist-info/licenses/LICENSE
zeptomail_python_api-0.1.5.dist-info/RECORD
