Metadata-Version: 2.4
Name: zeptomail-python-api
Version: 0.1.5
Summary: Python client for the ZeptoMail API
Project-URL: Homepage, https://github.com/NamiLinkLabs/zeptomail-python-api
Project-URL: Bug Tracker, https://github.com/NamiLinkLabs/zeptomail-python-api/issues
Project-URL: Documentation, https://github.com/NamiLinkLabs/zeptomail-python-api#readme
Author-email: Mate Valko <zeptomail@namilink.com>
License: MIT License
License-File: LICENSE
Keywords: api,client,email,zeptomail
Classifier: Development Status :: 4 - Beta
Classifier: Intended Audience :: Developers
Classifier: License :: OSI Approved :: MIT License
Classifier: Programming Language :: Python :: 3
Classifier: Programming Language :: Python :: 3.9
Classifier: Programming Language :: Python :: 3.10
Classifier: Programming Language :: Python :: 3.11
Classifier: Programming Language :: Python :: 3.12
Classifier: Topic :: Communications :: Email
Requires-Python: >=3.9
Requires-Dist: python-dotenv>=1.0.1
Requires-Dist: requests>=2.32.3
Provides-Extra: webhooks
Requires-Dist: fastapi>=0.115.8; extra == 'webhooks'
Requires-Dist: pydantic>=2.10.6; extra == 'webhooks'
Requires-Dist: uvicorn>=0.34.0; extra == 'webhooks'
